doctor/__init__.py
doctor/cli.py
doctor/version.py
doctor/rules/__init__.py
doctor/rules/compression.py
doctor/rules/hypertable.py
doctor/rules/index.py
timescale_doctor-0.1.1.dist-info/LICENSE
timescale_doctor-0.1.1.dist-info/METADATA
timescale_doctor-0.1.1.dist-info/WHEEL
timescale_doctor-0.1.1.dist-info/entry_points.txt
timescale_doctor-0.1.1.dist-info/top_level.txt
timescale_doctor-0.1.1.dist-info/RECORD
