Metadata-Version: 2.1
Name: timescale-doctor
Version: 0.1.1
Summary: Analyze a database and provide recommendations
Author: Mats Kindahl
Author-email: mats@timescale.com
License: Apache 2
Project-URL: Documentation, https://pip.pypa.io
Project-URL: Source, https://github.com/timescale/doctor
Project-URL: Changelog, https://pip.pypa.io/en/stable/news/
Keywords: postgresql timescale
Classifier: Development Status :: 3 - Alpha
Classifier: Intended Audience :: Developers
Classifier: License :: OSI Approved :: Apache Software License
Classifier: Topic :: Utilities
Classifier: Programming Language :: Python
Classifier: Programming Language :: Python :: 3
Classifier: Programming Language :: Python :: 3 :: Only
License-File: LICENSE
Requires-Dist: psycopg2
